lavista/__init__.py
lavista/main.py
lavista-0.1.dist-info/METADATA
lavista-0.1.dist-info/WHEEL
lavista-0.1.dist-info/top_level.txt
lavista-0.1.dist-info/RECORD
