Metadata-Version: 2.1
Name: lavista
Version: 0.1
Requires-Dist: numpy
Requires-Dist: pandas
Requires-Dist: scikit-learn
Requires-Dist: matplotlib
